{"components_alert.md":"28b161b6","components_avatar.md":"51c25a22","components_back-top.md":"fd7b9ddd","components_badge.md":"cf1ced25","components_breadcrumb.md":"0762fb12","components_button.md":"aba65b02","components_calendar.md":"bc3b1e68","components_card.md":"ad7f809b","components_checkbox.md":"25c46a7d","components_close-btn.md":"170d7f20","components_collapse-animation.md":"9a30ee41","components_color.md":"2e89fcd1","components_date-picker.md":"fcfb7ead","components_dialog.md":"fb5e71ec","components_divider.md":"1668a704","components_drawer.md":"513b98ed","components_dropdown.md":"476f3374","components_empty.md":"b4c54a80","components_expand-card.md":"58bb1642","components_image-preview.md":"9bc4d456","components_image.md":"7de4a73c","components_input-number.md":"80e6b670","components_input.md":"bc06a6ff","components_layout.md":"ee45fd32","components_link.md":"fd6c3deb","components_list.md":"188dba8f","components_loading-bar.md":"37e57e0d","components_loading.md":"18d0e237","components_menu.md":"8fd78587","components_message.md":"1a01c4c9","components_notification.md":"51297167","components_page-header.md":"c9ba4ea9","components_pagination.md":"abb1df77","components_popup.md":"170eb598","components_progress.md":"fbcae467","components_radio.md":"ab2e30cf","components_rate.md":"276c60b6","components_ripple.md":"a21079cd","components_select.md":"f901df3b","components_skeleton.md":"1b69f455","components_slider.md":"90800f1a","components_space.md":"78d23df9","components_sticky-card.md":"3f5a76c2","components_svg-icon.md":"9a67aad0","components_swap.md":"7eed12cd","components_switch.md":"45de35bb","components_table.md":"d782ffad","components_tabs.md":"66cfdc01","components_tag.md":"3ea47cb1","components_text.md":"b1a2d5eb","components_textarea.md":"203a2334","components_time-picker.md":"1d9b0477","components_toolbar.md":"91667ba1","components_tooltip.md":"2c7875d5","components_tree.md":"6b6becd9","components_trigger.md":"e24da06b","components_up-load.md":"21332571","components_watermark.md":"f2228eea","docs_changelog.md":"f3059e55","docs_contributing.md":"88e89d81","docs_import.md":"b4433f40","docs_install.md":"592841c2","docs_introduce.md":"c64072ff","docs_join.md":"6dea1ec8","docs_milepost.md":"c7bebda1","index.md":"18665ef4","theme_start.md":"18afa662"}
