{"components_alert.md":"2beb19c1","components_avatar.md":"3d477d4e","components_back-top.md":"31bab1e3","components_badge.md":"bad5c63c","components_breadcrumb.md":"85408622","components_button.md":"8b1d2b1d","components_calendar.md":"0bb1b705","components_card.md":"a3805fe3","components_checkbox.md":"54efc82b","components_close-btn.md":"476ee3ce","components_color.md":"226f657f","components_dialog.md":"2cec3018","components_divider.md":"1e7adc35","components_drawer.md":"244f60ce","components_empty.md":"41b1a2e8","components_expand-card.md":"b20ef482","components_image-preview.md":"40b4d386","components_image.md":"13f7864d","components_input.md":"75081cb5","components_layout.md":"e6c6eb80","components_link.md":"2b71354b","components_list.md":"ca219397","components_loading-bar.md":"fab6039d","components_loading.md":"ae59a7a4","components_message.md":"ec558c73","components_notification.md":"d7f9de19","components_page-header.md":"44cefa02","components_popup.md":"a7db3426","components_progress.md":"3bb4271e","components_radio.md":"4572aef2","components_rate.md":"aff71b8a","components_ripple.md":"a937609a","components_skeleton.md":"958d88b1","components_space.md":"45a6966a","components_sticky-card.md":"abb0f90a","components_svg-icon.md":"51817791","components_swap.md":"dc32b8e1","components_switch.md":"a17df044","components_tag.md":"dacf08c0","components_text.md":"5feb2ddc","components_toolbar.md":"e40e1548","components_tooltip.md":"9bdd930a","components_tree.md":"760ea4f6","components_waterfall.md":"c5317aaf","components_watermark.md":"223ed609","docs_changelog.md":"b6e647a8","docs_contributing.md":"abf0662b","docs_import.md":"decabd76","docs_install.md":"3297f80a","docs_introduce.md":"ea8a2b7f","docs_join.md":"d5094ff6","docs_milepost.md":"52ff561c","index.md":"ddd894d2"}
