{"components_alert.md":"e771009b","components_avatar.md":"1c0ef82d","components_back-top.md":"f5e56b07","components_badge.md":"d120e43c","components_breadcrumb.md":"563c0d05","components_button.md":"98e94308","components_calendar.md":"b8f15429","components_card.md":"89268049","components_checkbox.md":"87423d85","components_close-btn.md":"d08e64b3","components_color.md":"0c5a742f","components_dialog.md":"14a4daa5","components_divider.md":"3ae36e74","components_drawer.md":"e32574ea","components_dropdown.md":"501eec60","components_empty.md":"e0ef7d4b","components_expand-card.md":"efaffe86","components_image-preview.md":"4d11e8c1","components_image.md":"0f455080","components_input.md":"20d57807","components_layout.md":"bafbebe2","components_link.md":"107b44a5","components_list.md":"6f44f525","components_loading-bar.md":"cd5f527c","components_loading.md":"b0f23504","components_message.md":"90bf6d52","components_notification.md":"0b8741bc","components_page-header.md":"349ea61e","components_pagination.md":"8c567f4f","components_popup.md":"94fdfd17","components_progress.md":"7d8cb49d","components_radio.md":"4eaa6803","components_rate.md":"ef407a23","components_ripple.md":"6d2a9f84","components_select.md":"f0a0d075","components_skeleton.md":"a6f9dece","components_space.md":"bf2ec9d5","components_sticky-card.md":"74437275","components_svg-icon.md":"55a3935a","components_swap.md":"ecdcbb3e","components_switch.md":"821e82d9","components_table.md":"7ab6b1fa","components_tabs.md":"75973243","components_tag.md":"bfb77adf","components_text.md":"c2f792e5","components_textarea.md":"c5079c67","components_toolbar.md":"f87fec31","components_tooltip.md":"51925cc7","components_tree.md":"bd56b4cc","components_up-load.md":"157daccf","components_watermark.md":"bc9e65a8","docs_changelog.md":"c3c2779c","docs_contributing.md":"46950452","docs_import.md":"d4aaa94e","docs_install.md":"704ec95d","docs_introduce.md":"4aaeb3d9","docs_join.md":"af739ffc","docs_milepost.md":"65a74496","index.md":"5eee24e1","theme_start.md":"47ff279c"}
