{"components_alert.md":"d1a468df","components_avatar.md":"a2be3e02","components_back-top.md":"d207ef72","components_badge.md":"a64dcea6","components_breadcrumb.md":"1b8dec10","components_button.md":"0fbb1707","components_calendar.md":"a9cc2cd7","components_card.md":"1e80fa98","components_checkbox.md":"5423e91c","components_close-btn.md":"3b549f18","components_color.md":"2d85dea2","components_dialog.md":"0eadfba1","components_divider.md":"5e1109e8","components_drawer.md":"64068b6d","components_empty.md":"4dc61d4f","components_expand-card.md":"bd2325d9","components_image-preview.md":"8ebe0972","components_image.md":"eaf3a9ed","components_input.md":"d99619d8","components_layout.md":"5b24c2f6","components_link.md":"cf7c83ff","components_list.md":"781eb808","components_loading-bar.md":"18b9ae70","components_loading.md":"ad62cbba","components_message.md":"444ce2ba","components_notification.md":"4e3e6d87","components_page-header.md":"cadc76fd","components_popup.md":"7b61cf96","components_progress.md":"f45294c5","components_radio.md":"8fd7ab3f","components_rate.md":"9237e118","components_ripple.md":"cc045de4","components_skeleton.md":"e814f455","components_space.md":"6d2213db","components_sticky-card.md":"bf752ec7","components_svg-icon.md":"e2d68c2b","components_swap.md":"682a1436","components_switch.md":"253f4cea","components_tag.md":"90ffb266","components_text.md":"78709b32","components_toolbar.md":"4654e7a1","components_tooltip.md":"fe8c63f1","components_tree.md":"f8e7d2c9","components_up-load.md":"caef4dae","components_watermark.md":"6fd9816e","docs_changelog.md":"158738ca","docs_contributing.md":"a15c3c54","docs_import.md":"9ed4667d","docs_install.md":"1610f702","docs_introduce.md":"db8efeda","docs_join.md":"46e3a866","docs_milepost.md":"d189f7e2","index.md":"6ee0e955"}
